{"default": {"name": "default", "time_cut": 1530624943.91532, "leagues": null, "replays_dire": [4150068226, 4131325578, 4131577738, 4138748557, 4148931989, 4124539033, 4112437916, 4147189535, 4148769848, 4117575225, 4149128262, 4112561096, 4135682894, 4111391312, 4135318100, 4138539349, 4136828506, 4136945756, 4109293789, 4139904606, 4114463071, 4148660449, 4112766947, 4151909603, 4131895141, 4111243111, 4133535723, 4109710706, 4114362738, 4113081719, 4133671928], "replays_radiant": [4114276224, 4140029184, 4133426183, 4152095495, 4151789329, 4135476627, 4131446436, 4135220260, 4109599274, 4146971050, 4111182515, 4109400627, 4138654389, 4141524918, 4135634500, 4125862987, 4110906830, 4113135823, 4131810128, 4125793617, 4136676440, 4124664293, 4150163431, 4149046767, 4112881138], "plot_dire_drafts": "Team Lithium\\default\\dire\\drafts.png", "plot_radiant_drafts": "Team Lithium\\default\\radiant\\drafts.png", "plot_pos_dire": ["Team Lithium\\default\\dire\\Madara.png", "Team Lithium\\default\\dire\\MagE.png", "Team Lithium\\default\\dire\\KheZu.png", "Team Lithium\\default\\dire\\Maybe Next Time .png", "Team Lithium\\default\\dire\\Peksu.png"], "plot_pos_radiant": ["Team Lithium\\default\\radiant\\Madara.png", "Team Lithium\\default\\radiant\\MagE.png", "Team Lithium\\default\\radiant\\KheZu.png", "Team Lithium\\default\\radiant\\Maybe Next Time .png", "Team Lithium\\default\\radiant\\Peksu.png"], "player_names": ["Madara", "MagE", "KheZu", "Maybe Next Time ", "Peksu"], "plot_ward_dire": ["Team Lithium\\default\\dire\\wards_pregame.png", "Team Lithium\\default\\dire\\wards_0to4.png", "Team Lithium\\default\\dire\\wards_4to8.png"], "plot_ward_radiant": ["Team Lithium\\default\\radiant\\wards_pregame.png", "Team Lithium\\default\\radiant\\wards_0to4.png", "Team Lithium\\default\\radiant\\wards_4to8.png"], "plot_ward_names": ["Pregame", "0 to 4 mins", "4 to 8 mins"], "plot_scan_dire": "Team Lithium\\default\\dire\\scan_summary.png", "plot_scan_radiant": "Team Lithium\\default\\radiant\\scan_summary.png", "plot_smoke_dire": "Team Lithium\\default\\dire\\smoke_summary.png", "plot_smoke_radiant": "Team Lithium\\default\\radiant\\smoke_summary.png", "plot_draft_summary": "Team Lithium\\default\\draft_summary.png", "plot_hero_picks": "Team Lithium\\default\\hero_picks.png", "plot_pair_picks": "Team Lithium\\default\\pick_pairs.png", "plot_pick_context": "Team Lithium\\default\\pick_context.png", "plot_win_rate": "Team Lithium\\default\\hero_win_rate.png", "plot_rune_control": "Team Lithium\\default\\rune_control.png", "stat_win_rate": "<table border=\"1\" class=\"dataframe\">\n  <thead>\n    <tr style=\"text-align: right;\">\n      <th></th>\n      <th>First Rate</th>\n      <th>Second Rate</th>\n      <th>All Rate</th>\n    </tr>\n  </thead>\n  <tbody>\n    <tr>\n      <th>Dire</th>\n      <td>0.45</td>\n      <td>0.55</td>\n      <td>0.48</td>\n    </tr>\n    <tr>\n      <th>Radiant</th>\n      <td>0.75</td>\n      <td>0.53</td>\n      <td>0.60</td>\n    </tr>\n    <tr>\n      <th>All</th>\n      <td>0.54</td>\n      <td>0.54</td>\n      <td>0.54</td>\n    </tr>\n  </tbody>\n</table>"}}